nb_tokenizer.py
nb_tokenizer-0.1.0.dist-info/METADATA
nb_tokenizer-0.1.0.dist-info/WHEEL
nb_tokenizer-0.1.0.dist-info/RECORD
