Metadata-Version: 2.1
Name: nb_tokenizer
Version: 0.1.0
Summary: Tokenization of Norwegian texts
License: MIT
Author: The DH-lab at the National Library of Norway
Author-email: dh-lab@nb.no
Requires-Python: >=3.7,<4.0
Classifier: License :: OSI Approved :: MIT License
Classifier: Programming Language :: Python :: 3
Classifier: Programming Language :: Python :: 3.7
Classifier: Programming Language :: Python :: 3.8
Classifier: Programming Language :: Python :: 3.9
Classifier: Programming Language :: Python :: 3.10
Classifier: Programming Language :: Python :: 3.11
